easyorm/__init__.py
easyorm/db_pool.py
easyorm/orm.py
easyorm/page.py
easyorm/conf/config.yml
easyorm_mysql-1.0.0.dist-info/METADATA
easyorm_mysql-1.0.0.dist-info/WHEEL
easyorm_mysql-1.0.0.dist-info/top_level.txt
easyorm_mysql-1.0.0.dist-info/RECORD
